Dockerfile
LICENSE
MANIFEST.in
README.md
requirements.txt
setup.py
test-requirements.txt
docker_cloud.egg-info/PKG-INFO
docker_cloud.egg-info/SOURCES.txt
docker_cloud.egg-info/dependency_links.txt
docker_cloud.egg-info/entry_points.txt
docker_cloud.egg-info/requires.txt
docker_cloud.egg-info/top_level.txt
dockercloudcli/__init__.py
dockercloudcli/cli.py
dockercloudcli/commands.py
dockercloudcli/exceptions.py
dockercloudcli/interpolation.py
dockercloudcli/parsers.py
dockercloudcli/utils.py
tests/__init__.py
tests/test_commands.py
tests/test_parser.py
tests/test_utils.py