Metadata-Version: 1.0
Name: docker-cloud
Version: 1.0.9
Summary: CLI for Docker Cloud
Home-page: http://cloud.docker.com/
Author: Docker, Inc.
Author-email: info@docker.com
License: Apache v2
Keywords: docker cloud cli
Platform: UNKNOWN
